jupyterlab_miami_nights/__init__.py
jupyterlab_miami_nights/_version.py
jupyterlab_miami_nights/extension/install.json
jupyterlab_miami_nights/labextension/package.json
jupyterlab_miami_nights/labextension/static/568.266d1e04caf5449102d7.js
jupyterlab_miami_nights/labextension/static/remoteEntry.382ac9f028a244bc2d44.js
jupyterlab_miami_nights/labextension/static/style.js
jupyterlab_miami_nights/labextension/static/third-party-licenses.json
jupyterlab_miami_nights/labextension/themes/@timkpaine/jupyterlab_miami_nights/2967dd73df838d2a2d39.ttf
jupyterlab_miami_nights/labextension/themes/@timkpaine/jupyterlab_miami_nights/80922933add5aaad3870.ttf
jupyterlab_miami_nights/labextension/themes/@timkpaine/jupyterlab_miami_nights/b5e5e677f7c3567440b0.woff2
jupyterlab_miami_nights/labextension/themes/@timkpaine/jupyterlab_miami_nights/index.css
jupyterlab_miami_nights/labextension/themes/@timkpaine/jupyterlab_miami_nights/index.js
jupyterlab_miami_nights/tests/test_labextension.py
jupyterlab_miami_nights-0.4.2.data/data/share/jupyter/labextensions/@timkpaine/jupyterlab_miami_nights/package.json
jupyterlab_miami_nights-0.4.2.data/data/share/jupyter/labextensions/@timkpaine/jupyterlab_miami_nights/static/568.266d1e04caf5449102d7.js
jupyterlab_miami_nights-0.4.2.data/data/share/jupyter/labextensions/@timkpaine/jupyterlab_miami_nights/static/remoteEntry.382ac9f028a244bc2d44.js
jupyterlab_miami_nights-0.4.2.data/data/share/jupyter/labextensions/@timkpaine/jupyterlab_miami_nights/static/style.js
jupyterlab_miami_nights-0.4.2.data/data/share/jupyter/labextensions/@timkpaine/jupyterlab_miami_nights/static/third-party-licenses.json
jupyterlab_miami_nights-0.4.2.data/data/share/jupyter/labextensions/@timkpaine/jupyterlab_miami_nights/themes/@timkpaine/jupyterlab_miami_nights/2967dd73df838d2a2d39.ttf
jupyterlab_miami_nights-0.4.2.data/data/share/jupyter/labextensions/@timkpaine/jupyterlab_miami_nights/themes/@timkpaine/jupyterlab_miami_nights/80922933add5aaad3870.ttf
jupyterlab_miami_nights-0.4.2.dist-info/METADATA
jupyterlab_miami_nights-0.4.2.dist-info/WHEEL
jupyterlab_miami_nights-0.4.2.dist-info/licenses/LICENSE
jupyterlab_miami_nights-0.4.2.dist-info/RECORD
