Metadata-Version: 2.3
Name: jupyterlab_miami_nights
Version: 0.4.2
Summary: A glowing 80s theme based on Synthwave '84 and  JupyterLab's Neon Night theme by yeebc
Project-URL: Repository, https://github.com/timkpaine/jupyterlab_miami_nights
Project-URL: Homepage, https://github.com/timkpaine/jupyterlab_miami_nights
Author: the jupyterlab_miami_nights authors
License: BSD 3-Clause License
License-File: LICENSE
Keywords: Jupyter,JupyterLab
Classifier: Development Status :: 4 - Beta
Classifier: Framework :: Jupyter
Classifier: Framework :: Jupyter :: JupyterLab
Classifier: License :: OSI Approved :: Apache Software License
Classifier: Programming Language :: Python
Classifier: Programming Language :: Python :: 3
Classifier: Programming Language :: Python :: 3.7
Classifier: Programming Language :: Python :: 3.8
Classifier: Programming Language :: Python :: 3.9
Classifier: Programming Language :: Python :: 3.10
Classifier: Programming Language :: Python :: 3.11
Requires-Python: >=3.7
Requires-Dist: jupyterlab<5,>=4
Provides-Extra: develop
Requires-Dist: black>=23; extra == 'develop'
Requires-Dist: check-manifest; extra == 'develop'
Requires-Dist: pytest; extra == 'develop'
Requires-Dist: pytest-cov; extra == 'develop'
Requires-Dist: ruff; extra == 'develop'
Provides-Extra: test
Requires-Dist: pytest; extra == 'test'
Requires-Dist: pytest-cov; extra == 'test'
